runtime_introspect/__init__.py
runtime_introspect/__main__.py
runtime_introspect/_cli.py
runtime_introspect/_features.py
runtime_introspect/_status.py
runtime_introspect/py.typed
runtime_introspect-0.3.0.dist-info/licenses/LICENSE
runtime_introspect-0.3.0.dist-info/WHEEL
runtime_introspect-0.3.0.dist-info/METADATA
runtime_introspect-0.3.0.dist-info/RECORD
