Metadata-Version: 2.4
Name: runtime-introspect
Version: 0.3.0
Summary: A small Python library to seamlessly introspect interpreter features at runtime
Author: C.M.T. Robert
Requires-Python: >=3.10
License-Expression: GPL-3.0-only
Classifier: Intended Audience :: Developers
Classifier: Development Status :: 3 - Alpha
Classifier: Operating System :: POSIX :: Linux
Classifier: Operating System :: MacOS
Classifier: Operating System :: Microsoft :: Windows
Classifier: Programming Language :: Python :: Implementation :: CPython
Classifier: Programming Language :: Python :: 3
Classifier: Programming Language :: Python :: 3.10
Classifier: Programming Language :: Python :: 3.11
Classifier: Programming Language :: Python :: 3.12
Classifier: Programming Language :: Python :: 3.13
Classifier: Programming Language :: Python :: 3.14
Classifier: Programming Language :: Python :: 3.15
Classifier: Programming Language :: Python :: Free Threading :: 3 - Stable
Classifier: Topic :: Scientific/Engineering
Classifier: Typing :: Typed
License-File: LICENSE
Project-URL: Changelog, https://github.com/neutrinoceros/runtime-introspect/blob/main/CHANGELOG.md
Project-URL: Homepage, https://github.com/neutrinoceros/runtime-introspect
